.VERSION
AUTHORS.rst
CONTRIBUTING.rst
HISTORY.rst
LICENSE
MANIFEST.in
Pipfile
Pipfile.lock
README.rst
USAGE.rst
dev-requirements.txt
requirements.txt
setup.cfg
setup.py
docs/Makefile
docs/authors.rst
docs/conf.py
docs/contributing.rst
docs/history.rst
docs/index.rst
docs/installation.rst
docs/readme.rst
docs/usage.rst
sonosaudioservicelib/.VERSION
sonosaudioservicelib/AUTHORS.rst
sonosaudioservicelib/CONTRIBUTING.rst
sonosaudioservicelib/HISTORY.rst
sonosaudioservicelib/LICENSE
sonosaudioservicelib/Pipfile
sonosaudioservicelib/Pipfile.lock
sonosaudioservicelib/README.rst
sonosaudioservicelib/USAGE.rst
sonosaudioservicelib/__init__.py
sonosaudioservicelib/_version.py
sonosaudioservicelib/dev-requirements.txt
sonosaudioservicelib/requirements.txt
sonosaudioservicelib/sonosaudioservicelib.py
sonosaudioservicelib/sonosaudioservicelibexceptions.py
sonosaudioservicelib.egg-info/PKG-INFO
sonosaudioservicelib.egg-info/SOURCES.txt
sonosaudioservicelib.egg-info/dependency_links.txt
sonosaudioservicelib.egg-info/not-zip-safe
sonosaudioservicelib.egg-info/top_level.txt
tests/test_sonosaudioservicelib.py