Metadata-Version: 2.1
Name: sonosaudioservicelib
Version: 0.3.0
Summary: A template for Sonos Audio services
Home-page: https://github.com/costastf/sonosaudioservicelib
Author: Jenda Brands
Author-email: jenda@brnds.eu
License: MIT
Keywords: sonosaudioservicelib
Classifier: Development Status :: 2 - Pre-Alpha
Classifier: Intended Audience :: Developers
Classifier: License :: OSI Approved :: MIT License
Classifier: Natural Language :: English
Classifier: Programming Language :: Python :: 3.9
License-File: LICENSE
License-File: AUTHORS.rst
